AUTHORS
CHANGES
LICENSE
MANIFEST.in
README
VERSION
requirements.txt
setup.py
python_reformat.egg-info/PKG-INFO
python_reformat.egg-info/SOURCES.txt
python_reformat.egg-info/dependency_links.txt
python_reformat.egg-info/top_level.txt
reformat/__init__.py