Metadata-Version: 1.0
Name: python-reformat
Version: 0.1
Summary: python-reformat
Home-page: https://github.com/lvjiyong/
Author: lvjiyong
Author-email: lvjiyong@gmail.com
License: GPL
Platform: any
